django_content_edit-1.7.dist-info/RECORD
django_content_edit-1.7.dist-info/top_level.txt
django_content_edit-1.7.dist-info/metadata.json
django_content_edit-1.7.dist-info/DESCRIPTION.rst
django_content_edit-1.7.dist-info/WHEEL
django_content_edit-1.7.dist-info/METADATA
content_edit/__init__.py
content_edit/views.py
content_edit/admin.py
content_edit/tests.py
content_edit/models.py
content_edit/urls.py
content_edit/settings.py
content_edit/migrations/__init__.py
content_edit/migrations/0001_initial.py
content_edit/templatetags/__init__.py
content_edit/templatetags/content_edit_tags.py
content_edit/templates/content_edit/sample_content_edit.html
content_edit/static/content_edit/content_edit.js
content_edit/static/content_edit/ckeditor/README.md
content_edit/static/content_edit/ckeditor/contents.css
content_edit/static/content_edit/ckeditor/styles.js
content_edit/static/content_edit/ckeditor/build-config.js
content_edit/static/content_edit/ckeditor/LICENSE.md
content_edit/static/content_edit/ckeditor/config.js
content_edit/static/content_edit/ckeditor/ckeditor.js
content_edit/static/content_edit/ckeditor/CHANGES.md
content_edit/static/content_edit/ckeditor/.bower.json
content_edit/static/content_edit/ckeditor/samples/index.html
content_edit/static/content_edit/ckeditor/samples/inlinebycode.html
content_edit/static/content_edit/ckeditor/samples/xhtmlstyle.html
content_edit/static/content_edit/ckeditor/samples/inlinetextarea.html
content_edit/static/content_edit/ckeditor/samples/sample.js
content_edit/static/content_edit/ckeditor/samples/tabindex.html
content_edit/static/content_edit/ckeditor/samples/readonly.html
content_edit/static/content_edit/ckeditor/samples/uilanguages.html
content_edit/static/content_edit/ckeditor/samples/sample_posteddata.php
content_edit/static/content_edit/ckeditor/samples/api.html
content_edit/static/content_edit/ckeditor/samples/sample.css
content_edit/static/content_edit/ckeditor/samples/ajax.html
content_edit/static/content_edit/ckeditor/samples/jquery.html
content_edit/static/content_edit/ckeditor/samples/replacebyclass.html
content_edit/static/content_edit/ckeditor/samples/appendto.html
content_edit/static/content_edit/ckeditor/samples/divreplace.html
