Metadata-Version: 2.0
Name: django-content-edit
Version: 1.7
Summary: A very simple way to let users edit content on the front end of a website.
Home-page: https://github.com/burke-software/django-content-edit
Author: David Burke
Author-email: david@burkesoftware.com
License: BSD
Keywords: django cms content ajax
Platform: UNKNOWN
Classifier: Development Status :: 5 - Production/Stable
Classifier: Environment :: Web Environment
Classifier: Framework :: Django
Classifier: Programming Language :: Python
Classifier: Intended Audience :: Developers
Classifier: Intended Audience :: System Administrators
Classifier: License :: OSI Approved :: BSD License
Requires-Dist: django
Requires-Dist: django-ckeditor-updated
Requires-Dist: django-reversion
